ryanlocal/__init__.py
ryanlocal/__main__.py
ryanlocal-0.2.0.dist-info/METADATA
ryanlocal-0.2.0.dist-info/WHEEL
ryanlocal-0.2.0.dist-info/RECORD
