Metadata-Version: 2.1
Name: ryanlocal
Version: 0.2.0
Summary: 
Author: arr
Author-email: ryan.despain@dave.com
Requires-Python: >=3.9,<4.0
Classifier: Programming Language :: Python :: 3
Classifier: Programming Language :: Python :: 3.9
Classifier: Programming Language :: Python :: 3.10
Classifier: Programming Language :: Python :: 3.11
Requires-Dist: requests (>=2.28.2,<3.0.0)
